odoo10_addon_shopinvader_elasticsearch-10.0.1.0.4-nspkg.pth
odoo/addons/shopinvader_elasticsearch/__init__.py
odoo/addons/shopinvader_elasticsearch/__manifest__.py
odoo/addons/shopinvader_elasticsearch/components/__init__.py
odoo/addons/shopinvader_elasticsearch/components/exporter.py
odoo/addons/shopinvader_elasticsearch/data/ir_export_product.xml
odoo/addons/shopinvader_elasticsearch/demo/backend_demo.xml
odoo/addons/shopinvader_elasticsearch/demo/index_config_demo.xml
odoo/addons/shopinvader_elasticsearch/models/__init__.py
odoo/addons/shopinvader_elasticsearch/models/shopinvader_product.py
odoo/addons/shopinvader_elasticsearch/tests/__init__.py
odoo/addons/shopinvader_elasticsearch/tests/test_shopinvader_elasticsearch.py
odoo/addons/shopinvader_elasticsearch/tests/cassettes/TestElasticsearchBackend.test_10_export_one_product.yaml
odoo/addons/shopinvader_elasticsearch/tests/cassettes/TestElasticsearchBackend.test_20_export_all_products.yaml
odoo/addons/shopinvader_elasticsearch/tests/cassettes/TestElasticsearchBackend.test_30_export_all_categories.yaml
odoo10_addon_shopinvader_elasticsearch-10.0.1.0.4.dist-info/METADATA
odoo10_addon_shopinvader_elasticsearch-10.0.1.0.4.dist-info/WHEEL
odoo10_addon_shopinvader_elasticsearch-10.0.1.0.4.dist-info/namespace_packages.txt
odoo10_addon_shopinvader_elasticsearch-10.0.1.0.4.dist-info/top_level.txt
odoo10_addon_shopinvader_elasticsearch-10.0.1.0.4.dist-info/RECORD
